essencia_pack/__init__.py
essencia_pack/__main__.py
essencia_pack/auth.py
essencia_pack/calendar.py
essencia_pack/core/__init__.py
essencia_pack/core/auth/__init__.py
essencia_pack/core/auth/main.py
essencia_pack/core/auth/user.py
essencia_pack/core/db/.env
essencia_pack/core/db/__init__.py
essencia_pack/core/db/base.py
essencia_pack/core/middleware/__init__.py
essencia_pack/core/middleware/base.py
essencia_pack/core/middleware/timing.py
essencia_pack/core/models/__init__.py
essencia_pack/core/models/abstract.py
essencia_pack/core/models/assistant.py
essencia_pack/core/models/base.py
essencia_pack/core/models/care.py
essencia_pack/core/models/patient.py
essencia_pack/core/models/provider.py
essencia_pack/deta_api/.env
essencia_pack/deta_api/__init__.py
essencia_pack/deta_api/async_api/__init__.py
essencia_pack/deta_api/async_api/main.py
essencia_pack/deta_api/sync_api/__init__.py
essencia_pack/deta_api/sync_api/main.py
essencia_pack/gender.py
essencia_pack/licence.py
essencia_pack/main.py
essencia_pack/models/__init__.py
essencia_pack/models/_base.py
essencia_pack/models/patient.py
essencia_pack/parser.py
essencia_pack/patient.py
essencia_pack/places.py
essencia_pack/static/style.css
essencia_pack/ws.py
essencia_pack-0.1.5.dist-info/WHEEL
essencia_pack-0.1.5.dist-info/METADATA
essencia_pack-0.1.5.dist-info/RECORD
