Metadata-Version: 2.1
Name: essencia-pack
Version: 0.1.5
Summary: 
Author: arantesdv
Author-email: arantesdv@me.com
Requires-Python: >=3.7,<4.0
Classifier: Programming Language :: Python :: 3
Classifier: Programming Language :: Python :: 3.7
Classifier: Programming Language :: Python :: 3.8
Classifier: Programming Language :: Python :: 3.9
Requires-Dist: Jinja2 (>=2.11.3,<3.0.0)
Requires-Dist: PyYAML (>=5.4.1,<6.0.0)
Requires-Dist: SQLAlchemy (==1.3.9)
Requires-Dist: aiofiles (>=0.6.0,<0.7.0)
Requires-Dist: aiosqlite (>=0.17.0,<0.18.0)
Requires-Dist: apispec (>=4.4.0,<5.0.0)
Requires-Dist: databases (>=0.4.3,<0.5.0)
Requires-Dist: deta (>=0.7,<0.8)
Requires-Dist: flama (>=0.16.0,<0.17.0)
Requires-Dist: graphene (>=2.1.8,<3.0.0)
Requires-Dist: httpx (>=0.17.1,<0.18.0)
Requires-Dist: itsdangerous (>=1.1.0,<2.0.0)
Requires-Dist: orm (>=0.1.5,<0.2.0)
Requires-Dist: pydantic (>=1.8.1,<2.0.0)
Requires-Dist: python-dotenv (>=0.17.0,<0.18.0)
Requires-Dist: python-forge (>=18.6.0,<19.0.0)
Requires-Dist: python-multipart (>=0.0.5,<0.0.6)
Requires-Dist: requests (>=2.25.1,<3.0.0)
Requires-Dist: starlette (>=0.14.2,<0.15.0)
Requires-Dist: uvicorn (>=0.13.4,<0.14.0)
